inputless_engines/__init__.py
inputless_engines/autonomous_mutation.py
inputless_engines/example_autonomous.py
inputless_engines/example_usage.py
inputless_engines/features/__init__.py
inputless_engines/features/autonomous_ab_testing.py
inputless_engines/fitness_functions.py
inputless_engines/genetic_operators.py
inputless_engines/metamorphic_code.py
inputless_engines/mutation_engine.py
inputless_engines/pattern_encoding.py
inputless_engines/reasoning_engine.py
inputless_engines/types.py
inputless_engines-1.0.2.dist-info/METADATA
inputless_engines-1.0.2.dist-info/WHEEL
inputless_engines-1.0.2.dist-info/entry_points.txt
inputless_engines-1.0.2.dist-info/RECORD
