Metadata-Version: 2.4
Name: inputless-engines
Version: 1.0.2
Summary: AI/ML engines with genetic algorithms, metamorphic code, and reasoning engines
Author: Inputless Team
Author-email: team@inputless.io
Requires-Python: >=3.11,<4.0
Classifier: Programming Language :: Python :: 3
Classifier: Programming Language :: Python :: 3.11
Classifier: Programming Language :: Python :: 3.12
Classifier: Programming Language :: Python :: 3.13
Classifier: Programming Language :: Python :: 3.14
Requires-Dist: deap (>=1.4.1,<2.0.0)
Requires-Dist: networkx (>=3.2.1,<4.0.0)
Requires-Dist: numpy (>=1.26.3,<2.0.0)
Requires-Dist: pydantic (>=2.5.3,<3.0.0)
Requires-Dist: scipy (>=1.11.4,<2.0.0)
